{"mRUBiS #2":{"Availability Item Filter":{"component_utility":"1.8189894035458565E-12","required_interface":"1","request":"356.0","replica":"9.0","failure_name":"None","perf_max":"15.202819009833096","importance":"17.0","reliability":"0.5","criticality":"28.0","sat_point":"0.022570903086534536","system_utility":"2256960.7635999564","adt":"1.1767631184962841","shop_utility":"234156.90931137747","uid":"_YlC64fdzEeyJ463rwa3DNQ","connectivity":"2.0","provided_interface":"1"},"Bid and Buy Service":{"component_utility":"1.8189894035458565E-12","required_interface":"5","request":"472.0","replica":"22.0","failure_name":"None","perf_max":"10.770027992759006","importance":"17.0","reliability":"0.5","criticality":"26.0","sat_point":"0.04465305064730373","system_utility":"2256960.7635999564","adt":"1.1371845306755326","shop_utility":"234156.90931137747","uid":"_YlC6ufdzEeyJ463rwa3DNQ","connectivity":"7.0","provided_interface":"2"},"Seller Reputation Item Filter":{"component_utility":"1.8189894035458565E-12","required_interface":"1","request":"68.0","replica":"5.0","failure_name":"None","perf_max":"7.517502967608486","importance":"17.0","reliability":"0.5","criticality":"17.0","sat_point":"0.059890151450378404","system_utility":"2256960.7635999564","adt":"1.4254878473267396","shop_utility":"234156.90931137747","uid":"_YlC66_dzEeyJ463rwa3DNQ","connectivity":"2.0","provided_interface":"1"},"User Management Service":{"component_utility":"1.8189894035458565E-12","required_interface":"4","request":"156.0","replica":"9.0","failure_name":"None","perf_max":"14.718096625108391","importance":"17.0","reliability":"0.5","criticality":"11.0","sat_point":"0.05591157017622139","system_utility":"2256960.7635999564","adt":"1.0117398224044207","shop_utility":"234156.90931137747","uid":"_YlC6pfdzEeyJ463rwa3DNQ","connectivity":"8.0","provided_interface":"4"},"Reputation Service":{"component_utility":"1.8189894035458565E-12","required_interface":"4","request":"201.0","replica":"10.0","failure_name":"None","perf_max":"10.266424585632524","importance":"17.0","reliability":"0.5","criticality":"28.0","sat_point":"0.04738655840883044","system_utility":"2256960.7635999564","adt":"1.0611475025350623","shop_utility":"234156.90931137747","uid":"_YlC6xfdzEeyJ463rwa3DNQ","connectivity":"5.0","provided_interface":"1"},"Comment Item Filter":{"component_utility":"1.8189894035458565E-12","required_interface":"1","request":"351.0","replica":"12.0","failure_name":"None","perf_max":"10.106530011534034","importance":"17.0","reliability":"0.5","criticality":"27.0","sat_point":"0.032603735506591465","system_utility":"2256960.7635999564","adt":"1.0367900009892557","shop_utility":"234156.90931137747","uid":"_YlC68fdzEeyJ463rwa3DNQ","connectivity":"2.0","provided_interface":"1"},"Recommendation Item Filter":{"component_utility":"1.8189894035458565E-12","required_interface":"1","request":"427.0","replica":"11.0","failure_name":"None","perf_max":"15.902749437653803","importance":"17.0","reliability":"0.5","criticality":"14.0","sat_point":"0.02486007911765469","system_utility":"2256960.7635999564","adt":"1.2328349953439666","shop_utility":"234156.90931137747","uid":"_YlC6_fdzEeyJ463rwa3DNQ","connectivity":"2.0","provided_interface":"1"},"Authentication Service":{"component_utility":"1.8189894035458565E-12","required_interface":"1","request":"75.0","replica":"2.0","failure_name":"None","perf_max":"8.256032202080931","importance":"17.0","reliability":"0.85","criticality":"12.0","sat_point":"0.025362685130688498","system_utility":"2256960.7635999564","adt":"1.0026522712987689","shop_utility":"234156.90931137747","uid":"_YlC6tvdzEeyJ463rwa3DNQ","connectivity":"2.0","provided_interface":"1"},"Persistence Service":{"component_utility":"1.8189894035458565E-12","required_interface":"0","request":"469.0","replica":"27.0","failure_name":"None","perf_max":"19.811111463712113","importance":"17.0","reliability":"0.5","criticality":"15.0","sat_point":"0.057073226231168075","system_utility":"2256960.7635999564","adt":"1.2084779206206786","shop_utility":"234156.90931137747","uid":"_YlC6y_dzEeyJ463rwa3DNQ","connectivity":"1.0","provided_interface":"1"},"Item Management Service":{"component_utility":"1.8189894035458565E-12","required_interface":"4","request":"337.0","replica":"19.0","failure_name":"None","perf_max":"18.45743490537749","importance":"17.0","reliability":"0.5","criticality":"12.0","sat_point":"0.05536998694174035","system_utility":"2256960.7635999564","adt":"1.3875655086002183","shop_utility":"234156.90931137747","uid":"_YlC6r_dzEeyJ463rwa3DNQ","connectivity":"6.0","provided_interface":"2"},"Buy Now Item Filter":{"component_utility":"1.8189894035458565E-12","required_interface":"1","request":"209.0","replica":"7.0","failure_name":"None","perf_max":"6.572020387423819","importance":"17.0","reliability":"0.5","criticality":"13.0","sat_point":"0.03223010259249852","system_utility":"2256960.7635999564","adt":"1.1589201720767166","shop_utility":"234156.90931137747","uid":"_YlC63PdzEeyJ463rwa3DNQ","connectivity":"2.0","provided_interface":"1"},"Query Service":{"component_utility":"1.8189894035458565E-12","required_interface":"1","request":"457.0","replica":"12.0","failure_name":"None","perf_max":"15.638260292962235","importance":"17.0","reliability":"0.5","criticality":"29.0","sat_point":"0.025129626474919963","system_utility":"2256960.7635999564","adt":"1.0139979966912067","shop_utility":"234156.90931137747","uid":"_YlC6zfdzEeyJ463rwa3DNQ","connectivity":"3.0","provided_interface":"2"},"Past Sales Item Filter":{"component_utility":"1.8189894035458565E-12","required_interface":"1","request":"77.0","replica":"4.0","failure_name":"None","perf_max":"18.788007171213202","importance":"17.0","reliability":"0.5","criticality":"17.0","sat_point":"0.04282965622198201","system_utility":"2256960.7635999564","adt":"1.4704720851248017","shop_utility":"234156.90931137747","uid":"_YlC61_dzEeyJ463rwa3DNQ","connectivity":"2.0","provided_interface":"1"},"Inventory Service":{"component_utility":"11472.080146059492","required_interface":"2","request":"256.0","replica":"8.0","failure_name":"None","perf_max":"10.234438874519249","importance":"17.0","reliability":"0.5","criticality":"22.0","sat_point":"0.030309544699775835","system_utility":"2256960.7635999564","adt":"1.096027115110735","shop_utility":"234156.90931137747","uid":"_YlC6wfdzEeyJ463rwa3DNQ","root_issue":"true","connectivity":"3.0","provided_interface":"1"},"Region Item Filter":{"component_utility":"1.8189894035458565E-12","required_interface":"1","request":"254.0","replica":"8.0","failure_name":"None","perf_max":"18.545001255145806","importance":"17.0","reliability":"0.5","criticality":"14.0","sat_point":"0.031169668271633928","system_utility":"2256960.7635999564","adt":"1.3947284388164114","shop_utility":"234156.90931137747","uid":"_YlC65vdzEeyJ463rwa3DNQ","connectivity":"2.0","provided_interface":"1"},"Category Item Filter":{"component_utility":"1.8189894035458565E-12","required_interface":"1","request":"460.0","replica":"20.0","failure_name":"None","perf_max":"7.311837387771401","importance":"17.0","reliability":"0.5","criticality":"19.0","sat_point":"0.042225913491143234","system_utility":"2256960.7635999564","adt":"1.3379895138930902","shop_utility":"234156.90931137747","uid":"_YlC69_dzEeyJ463rwa3DNQ","connectivity":"2.0","provided_interface":"1"},"Last Second Sales Item Filter":{"component_utility":"1.8189894035458565E-12","required_interface":"1","request":"250.0","replica":"14.0","failure_name":"None","perf_max":"13.387214882587912","importance":"17.0","reliability":"0.5","criticality":"25.0","sat_point":"0.05409054030995984","system_utility":"2256960.7635999564","adt":"1.386318912740616","shop_utility":"234156.90931137747","uid":"_YlC60fdzEeyJ463rwa3DNQ","connectivity":"2.0","provided_interface":"1"},"Future Sales Item Filter":{"component_utility":"1.8189894035458565E-12","required_interface":"1","request":"171.0","replica":"10.0","failure_name":"None","perf_max":"7.88766258577082","importance":"17.0","reliability":"0.5","criticality":"17.0","sat_point":"0.055229794880713085","system_utility":"2256960.7635999564","adt":"1.089317721222512","shop_utility":"234156.90931137747","uid":"_YlC7AvdzEeyJ463rwa3DNQ","connectivity":"2.0","provided_interface":"1"}},"mRUBiS #1":{"Availability Item Filter":{"component_utility":"0.0","required_interface":"1","request":"330.0","replica":"8.0","failure_name":"None","perf_max":"15.202819009833096","importance":"25.0","reliability":"0.5","criticality":"28.0","sat_point":"0.022570903086534536","system_utility":"2256960.7635999564","adt":"1.3338139815385488","shop_utility":"344447.5730457684","uid":"_YlC6QfdzEeyJ463rwa3DNQ","connectivity":"2.0","provided_interface":"1"},"Bid and Buy Service":{"component_utility":"0.0","required_interface":"5","request":"316.0","replica":"15.0","failure_name":"None","perf_max":"10.770027992759006","importance":"25.0","reliability":"0.5","criticality":"26.0","sat_point":"0.04465305064730373","system_utility":"2256960.7635999564","adt":"1.0269342675577946","shop_utility":"344447.5730457684","uid":"_YlC6GfdzEeyJ463rwa3DNQ","connectivity":"7.0","provided_interface":"2"},"Seller Reputation Item Filter":{"component_utility":"0.0","required_interface":"1","request":"145.0","replica":"9.0","failure_name":"None","perf_max":"7.517502967608486","importance":"25.0","reliability":"0.5","criticality":"17.0","sat_point":"0.059890151450378404","system_utility":"2256960.7635999564","adt":"1.3441606860644033","shop_utility":"344447.5730457684","uid":"_YlC6S_dzEeyJ463rwa3DNQ","connectivity":"2.0","provided_interface":"1"},"User Management Service":{"component_utility":"10108.217548432182","required_interface":"4","request":"319.0","replica":"18.0","failure_name":"None","perf_max":"14.718096625108391","importance":"25.0","reliability":"0.5","criticality":"11.0","sat_point":"0.05591157017622139","system_utility":"2256960.7635999564","adt":"1.0473881329836625","shop_utility":"344447.5730457684","uid":"_YlC6BfdzEeyJ463rwa3DNQ","root_issue":"true","connectivity":"8.0","provided_interface":"4"},"Reputation Service":{"component_utility":"0.0","required_interface":"4","request":"497.0","replica":"24.0","failure_name":"None","perf_max":"10.266424585632524","importance":"25.0","reliability":"0.5","criticality":"28.0","sat_point":"0.04738655840883044","system_utility":"2256960.7635999564","adt":"1.2739521131540281","shop_utility":"344447.5730457684","uid":"_YlC6JfdzEeyJ463rwa3DNQ","connectivity":"5.0","provided_interface":"1"},"Comment Item Filter":{"component_utility":"0.0","required_interface":"1","request":"222.0","replica":"8.0","failure_name":"None","perf_max":"10.106530011534034","importance":"25.0","reliability":"0.5","criticality":"27.0","sat_point":"0.032603735506591465","system_utility":"2256960.7635999564","adt":"1.1327469079861765","shop_utility":"344447.5730457684","uid":"_YlC6UfdzEeyJ463rwa3DNQ","connectivity":"2.0","provided_interface":"1"},"Recommendation Item Filter":{"component_utility":"0.0","required_interface":"1","request":"119.0","replica":"3.0","failure_name":"None","perf_max":"15.902749437653803","importance":"25.0","reliability":"0.5","criticality":"14.0","sat_point":"0.02486007911765469","system_utility":"2256960.7635999564","adt":"1.0352029332910744","shop_utility":"344447.5730457684","uid":"_YlC6XfdzEeyJ463rwa3DNQ","connectivity":"2.0","provided_interface":"1"},"Authentication Service":{"component_utility":"0.0","required_interface":"1","request":"55.0","replica":"2.0","failure_name":"None","perf_max":"8.256032202080931","importance":"25.0","reliability":"0.85","criticality":"12.0","sat_point":"0.025362685130688498","system_utility":"2256960.7635999564","adt":"1.3144877098054695","shop_utility":"344447.5730457684","uid":"_YlC6FvdzEeyJ463rwa3DNQ","connectivity":"2.0","provided_interface":"1"},"Persistence Service":{"component_utility":"0.0","required_interface":"0","request":"399.0","replica":"23.0","failure_name":"None","perf_max":"19.811111463712113","importance":"25.0","reliability":"0.5","criticality":"15.0","sat_point":"0.057073226231168075","system_utility":"2256960.7635999564","adt":"1.07059518016126","shop_utility":"344447.5730457684","uid":"_YlC6K_dzEeyJ463rwa3DNQ","connectivity":"1.0","provided_interface":"1"},"Item Management Service":{"component_utility":"0.0","required_interface":"4","request":"433.0","replica":"24.0","failure_name":"None","perf_max":"18.45743490537749","importance":"25.0","reliability":"0.5","criticality":"12.0","sat_point":"0.05536998694174035","system_utility":"2256960.7635999564","adt":"1.0568056149569547","shop_utility":"344447.5730457684","uid":"_YlC6D_dzEeyJ463rwa3DNQ","connectivity":"6.0","provided_interface":"2"},"Buy Now Item Filter":{"component_utility":"0.0","required_interface":"1","request":"229.0","replica":"8.0","failure_name":"None","perf_max":"6.572020387423819","importance":"25.0","reliability":"0.5","criticality":"13.0","sat_point":"0.03223010259249852","system_utility":"2256960.7635999564","adt":"1.4627040587757265","shop_utility":"344447.5730457684","uid":"_YlC6PPdzEeyJ463rwa3DNQ","connectivity":"2.0","provided_interface":"1"},"Query Service":{"component_utility":"0.0","required_interface":"1","request":"209.0","replica":"6.0","failure_name":"None","perf_max":"15.638260292962235","importance":"25.0","reliability":"0.5","criticality":"29.0","sat_point":"0.025129626474919963","system_utility":"2256960.7635999564","adt":"1.1344203974800142","shop_utility":"344447.5730457684","uid":"_YlC6LfdzEeyJ463rwa3DNQ","connectivity":"3.0","provided_interface":"2"},"Past Sales Item Filter":{"component_utility":"0.0","required_interface":"1","request":"186.0","replica":"8.0","failure_name":"None","perf_max":"18.788007171213202","importance":"25.0","reliability":"0.5","criticality":"17.0","sat_point":"0.04282965622198201","system_utility":"2256960.7635999564","adt":"1.4814512696517181","shop_utility":"344447.5730457684","uid":"_YlC6N_dzEeyJ463rwa3DNQ","connectivity":"2.0","provided_interface":"1"},"Inventory Service":{"component_utility":"0.0","required_interface":"2","request":"206.0","replica":"7.0","failure_name":"None","perf_max":"10.234438874519249","importance":"25.0","reliability":"0.5","criticality":"22.0","sat_point":"0.030309544699775835","system_utility":"2256960.7635999564","adt":"1.3084860097075286","shop_utility":"344447.5730457684","uid":"_YlC6IfdzEeyJ463rwa3DNQ","connectivity":"3.0","provided_interface":"1"},"Region Item Filter":{"component_utility":"0.0","required_interface":"1","request":"79.0","replica":"3.0","failure_name":"None","perf_max":"18.545001255145806","importance":"25.0","reliability":"0.5","criticality":"14.0","sat_point":"0.031169668271633928","system_utility":"2256960.7635999564","adt":"1.2025295628293897","shop_utility":"344447.5730457684","uid":"_YlC6RvdzEeyJ463rwa3DNQ","connectivity":"2.0","provided_interface":"1"},"Category Item Filter":{"component_utility":"0.0","required_interface":"1","request":"452.0","replica":"20.0","failure_name":"None","perf_max":"7.311837387771401","importance":"25.0","reliability":"0.5","criticality":"19.0","sat_point":"0.042225913491143234","system_utility":"2256960.7635999564","adt":"1.0884489317354404","shop_utility":"344447.5730457684","uid":"_YlC6V_dzEeyJ463rwa3DNQ","connectivity":"2.0","provided_interface":"1"},"Last Second Sales Item Filter":{"component_utility":"0.0","required_interface":"1","request":"204.0","replica":"12.0","failure_name":"None","perf_max":"13.387214882587912","importance":"25.0","reliability":"0.5","criticality":"25.0","sat_point":"0.05409054030995984","system_utility":"2256960.7635999564","adt":"1.1538112096669004","shop_utility":"344447.5730457684","uid":"_YlC6MfdzEeyJ463rwa3DNQ","connectivity":"2.0","provided_interface":"1"},"Future Sales Item Filter":{"component_utility":"0.0","required_interface":"1","request":"315.0","replica":"18.0","failure_name":"None","perf_max":"7.88766258577082","importance":"25.0","reliability":"0.5","criticality":"17.0","sat_point":"0.055229794880713085","system_utility":"2256960.7635999564","adt":"1.420854414232301","shop_utility":"344447.5730457684","uid":"_YlC6YvdzEeyJ463rwa3DNQ","connectivity":"2.0","provided_interface":"1"}},"mRUBiS #10":{"Availability Item Filter":{"component_utility":"-9.094947017729282E-13","required_interface":"1","request":"244.0","replica":"6.0","failure_name":"None","perf_max":"15.202819009833096","importance":"10.0","reliability":"0.5","criticality":"28.0","sat_point":"0.022570903086534536","system_utility":"2256960.7635999564","adt":"1.3285106956012296","shop_utility":"137647.81813216198","uid":"_YlDiCvdzEeyJ463rwa3DNQ","connectivity":"2.0","provided_interface":"1"},"Bid and Buy Service":{"component_utility":"-9.094947017729282E-13","required_interface":"5","request":"409.0","replica":"19.0","failure_name":"None","perf_max":"10.770027992759006","importance":"10.0","reliability":"0.5","criticality":"26.0","sat_point":"0.04465305064730373","system_utility":"2256960.7635999564","adt":"1.1698186500472523","shop_utility":"137647.81813216198","uid":"_YlDh4vdzEeyJ463rwa3DNQ","connectivity":"7.0","provided_interface":"2"},"Seller Reputation Item Filter":{"component_utility":"-9.094947017729282E-13","required_interface":"1","request":"274.0","replica":"17.0","failure_name":"None","perf_max":"7.517502967608486","importance":"10.0","reliability":"0.5","criticality":"17.0","sat_point":"0.059890151450378404","system_utility":"2256960.7635999564","adt":"1.158016493742053","shop_utility":"137647.81813216198","uid":"_YlDiFPdzEeyJ463rwa3DNQ","connectivity":"2.0","provided_interface":"1"},"User Management Service":{"component_utility":"-9.094947017729282E-13","required_interface":"4","request":"161.0","replica":"10.0","failure_name":"None","perf_max":"14.718096625108391","importance":"10.0","reliability":"0.5","criticality":"11.0","sat_point":"0.05591157017622139","system_utility":"2256960.7635999564","adt":"1.3449023656757184","shop_utility":"137647.81813216198","uid":"_YlDhzvdzEeyJ463rwa3DNQ","connectivity":"8.0","provided_interface":"4"},"Reputation Service":{"component_utility":"-9.094947017729282E-13","required_interface":"4","request":"130.0","replica":"7.0","failure_name":"None","perf_max":"10.266424585632524","importance":"10.0","reliability":"0.5","criticality":"28.0","sat_point":"0.04738655840883044","system_utility":"2256960.7635999564","adt":"1.201142358747754","shop_utility":"137647.81813216198","uid":"_YlDh7vdzEeyJ463rwa3DNQ","connectivity":"5.0","provided_interface":"1"},"Comment Item Filter":{"component_utility":"-9.094947017729282E-13","required_interface":"1","request":"320.0","replica":"11.0","failure_name":"None","perf_max":"10.106530011534034","importance":"10.0","reliability":"0.5","criticality":"27.0","sat_point":"0.032603735506591465","system_utility":"2256960.7635999564","adt":"1.1080320993255308","shop_utility":"137647.81813216198","uid":"_YlDiGvdzEeyJ463rwa3DNQ","connectivity":"2.0","provided_interface":"1"},"Recommendation Item Filter":{"component_utility":"-9.094947017729282E-13","required_interface":"1","request":"203.0","replica":"6.0","failure_name":"None","perf_max":"15.902749437653803","importance":"10.0","reliability":"0.5","criticality":"14.0","sat_point":"0.02486007911765469","system_utility":"2256960.7635999564","adt":"1.025360530746666","shop_utility":"137647.81813216198","uid":"_YlDiJvdzEeyJ463rwa3DNQ","connectivity":"2.0","provided_interface":"1"},"Authentication Service":{"component_utility":"6725.863082691745","required_interface":"1","request":"469.0","replica":"12.0","failure_name":"None","perf_max":"8.256032202080931","importance":"10.0","reliability":"0.85","criticality":"12.0","sat_point":"0.025362685130688498","system_utility":"2256960.7635999564","adt":"1.1059194206293899","shop_utility":"137647.81813216198","uid":"_YlDh3_dzEeyJ463rwa3DNQ","root_issue":"true","connectivity":"2.0","provided_interface":"1"},"Persistence Service":{"component_utility":"-9.094947017729282E-13","required_interface":"0","request":"233.0","replica":"14.0","failure_name":"None","perf_max":"19.811111463712113","importance":"10.0","reliability":"0.5","criticality":"15.0","sat_point":"0.057073226231168075","system_utility":"2256960.7635999564","adt":"1.0920507648867541","shop_utility":"137647.81813216198","uid":"_YlDh9PdzEeyJ463rwa3DNQ","connectivity":"1.0","provided_interface":"1"},"Item Management Service":{"component_utility":"-9.094947017729282E-13","required_interface":"4","request":"258.0","replica":"15.0","failure_name":"None","perf_max":"18.45743490537749","importance":"10.0","reliability":"0.5","criticality":"12.0","sat_point":"0.05536998694174035","system_utility":"2256960.7635999564","adt":"1.0874039249834528","shop_utility":"137647.81813216198","uid":"_YlDh2PdzEeyJ463rwa3DNQ","connectivity":"6.0","provided_interface":"2"},"Buy Now Item Filter":{"component_utility":"-9.094947017729282E-13","required_interface":"1","request":"227.0","replica":"8.0","failure_name":"None","perf_max":"6.572020387423819","importance":"10.0","reliability":"0.5","criticality":"13.0","sat_point":"0.03223010259249852","system_utility":"2256960.7635999564","adt":"1.398017551909223","shop_utility":"137647.81813216198","uid":"_YlDiBfdzEeyJ463rwa3DNQ","connectivity":"2.0","provided_interface":"1"},"Query Service":{"component_utility":"-9.094947017729282E-13","required_interface":"1","request":"360.0","replica":"10.0","failure_name":"None","perf_max":"15.638260292962235","importance":"10.0","reliability":"0.5","criticality":"29.0","sat_point":"0.025129626474919963","system_utility":"2256960.7635999564","adt":"1.085175133231198","shop_utility":"137647.81813216198","uid":"_YlDh9vdzEeyJ463rwa3DNQ","connectivity":"3.0","provided_interface":"2"},"Past Sales Item Filter":{"component_utility":"-9.094947017729282E-13","required_interface":"1","request":"116.0","replica":"5.0","failure_name":"None","perf_max":"18.788007171213202","importance":"10.0","reliability":"0.5","criticality":"17.0","sat_point":"0.04282965622198201","system_utility":"2256960.7635999564","adt":"1.116934276939944","shop_utility":"137647.81813216198","uid":"_YlDiAPdzEeyJ463rwa3DNQ","connectivity":"2.0","provided_interface":"1"},"Inventory Service":{"component_utility":"-9.094947017729282E-13","required_interface":"2","request":"55.0","replica":"2.0","failure_name":"None","perf_max":"10.234438874519249","importance":"10.0","reliability":"0.5","criticality":"22.0","sat_point":"0.030309544699775835","system_utility":"2256960.7635999564","adt":"1.0150729408861892","shop_utility":"137647.81813216198","uid":"_YlDh6vdzEeyJ463rwa3DNQ","connectivity":"3.0","provided_interface":"1"},"Region Item Filter":{"component_utility":"-9.094947017729282E-13","required_interface":"1","request":"328.0","replica":"11.0","failure_name":"None","perf_max":"18.545001255145806","importance":"10.0","reliability":"0.5","criticality":"14.0","sat_point":"0.031169668271633928","system_utility":"2256960.7635999564","adt":"1.3826925128154506","shop_utility":"137647.81813216198","uid":"_YlDiD_dzEeyJ463rwa3DNQ","connectivity":"2.0","provided_interface":"1"},"Category Item Filter":{"component_utility":"-9.094947017729282E-13","required_interface":"1","request":"412.0","replica":"18.0","failure_name":"None","perf_max":"7.311837387771401","importance":"10.0","reliability":"0.5","criticality":"19.0","sat_point":"0.042225913491143234","system_utility":"2256960.7635999564","adt":"1.4531221404940293","shop_utility":"137647.81813216198","uid":"_YlDiIPdzEeyJ463rwa3DNQ","connectivity":"2.0","provided_interface":"1"},"Last Second Sales Item Filter":{"component_utility":"-9.094947017729282E-13","required_interface":"1","request":"418.0","replica":"23.0","failure_name":"None","perf_max":"13.387214882587912","importance":"10.0","reliability":"0.5","criticality":"25.0","sat_point":"0.05409054030995984","system_utility":"2256960.7635999564","adt":"1.4016545570824113","shop_utility":"137647.81813216198","uid":"_YlDh-vdzEeyJ463rwa3DNQ","connectivity":"2.0","provided_interface":"1"},"Future Sales Item Filter":{"component_utility":"-9.094947017729282E-13","required_interface":"1","request":"380.0","replica":"21.0","failure_name":"None","perf_max":"7.88766258577082","importance":"10.0","reliability":"0.5","criticality":"17.0","sat_point":"0.055229794880713085","system_utility":"2256960.7635999564","adt":"1.4027995494236598","shop_utility":"137647.81813216198","uid":"_YlDiK_dzEeyJ463rwa3DNQ","connectivity":"2.0","provided_interface":"1"}},"mRUBiS #6":{"Availability Item Filter":{"component_utility":"0.0","required_interface":"1","request":"388.0","replica":"9.0","failure_name":"None","perf_max":"15.202819009833096","importance":"20.0","reliability":"0.5","criticality":"28.0","sat_point":"0.022570903086534536","system_utility":"2256960.7635999564","adt":"1.355159926842173","shop_utility":"275505.2129059975","uid":"_YlC9YfdzEeyJ463rwa3DNQ","connectivity":"2.0","provided_interface":"1"},"Bid and Buy Service":{"component_utility":"16786.32344784903","required_interface":"5","request":"296.0","replica":"14.0","failure_name":"None","perf_max":"10.770027992759006","importance":"20.0","reliability":"0.5","criticality":"26.0","sat_point":"0.04465305064730373","system_utility":"2256960.7635999564","adt":"1.4920220855019894","shop_utility":"275505.2129059975","uid":"_YlC9OfdzEeyJ463rwa3DNQ","root_issue":"true","connectivity":"7.0","provided_interface":"2"},"Seller Reputation Item Filter":{"component_utility":"0.0","required_interface":"1","request":"478.0","replica":"29.0","failure_name":"None","perf_max":"7.517502967608486","importance":"20.0","reliability":"0.5","criticality":"17.0","sat_point":"0.059890151450378404","system_utility":"2256960.7635999564","adt":"1.040271032752046","shop_utility":"275505.2129059975","uid":"_YlC9a_dzEeyJ463rwa3DNQ","connectivity":"2.0","provided_interface":"1"},"User Management Service":{"component_utility":"0.0","required_interface":"4","request":"291.0","replica":"17.0","failure_name":"None","perf_max":"14.718096625108391","importance":"20.0","reliability":"0.5","criticality":"11.0","sat_point":"0.05591157017622139","system_utility":"2256960.7635999564","adt":"1.0684195213810406","shop_utility":"275505.2129059975","uid":"_YlC9JfdzEeyJ463rwa3DNQ","connectivity":"8.0","provided_interface":"4"},"Reputation Service":{"component_utility":"0.0","required_interface":"4","request":"272.0","replica":"13.0","failure_name":"None","perf_max":"10.266424585632524","importance":"20.0","reliability":"0.5","criticality":"28.0","sat_point":"0.04738655840883044","system_utility":"2256960.7635999564","adt":"1.2122243298397561","shop_utility":"275505.2129059975","uid":"_YlC9RfdzEeyJ463rwa3DNQ","connectivity":"5.0","provided_interface":"1"},"Comment Item Filter":{"component_utility":"0.0","required_interface":"1","request":"418.0","replica":"14.0","failure_name":"None","perf_max":"10.106530011534034","importance":"20.0","reliability":"0.5","criticality":"27.0","sat_point":"0.032603735506591465","system_utility":"2256960.7635999564","adt":"1.4389911011628773","shop_utility":"275505.2129059975","uid":"_YlC9cfdzEeyJ463rwa3DNQ","connectivity":"2.0","provided_interface":"1"},"Recommendation Item Filter":{"component_utility":"0.0","required_interface":"1","request":"484.0","replica":"13.0","failure_name":"None","perf_max":"15.902749437653803","importance":"20.0","reliability":"0.5","criticality":"14.0","sat_point":"0.02486007911765469","system_utility":"2256960.7635999564","adt":"1.171612210578066","shop_utility":"275505.2129059975","uid":"_YlC9ffdzEeyJ463rwa3DNQ","connectivity":"2.0","provided_interface":"1"},"Authentication Service":{"component_utility":"0.0","required_interface":"1","request":"296.0","replica":"8.0","failure_name":"None","perf_max":"8.256032202080931","importance":"20.0","reliability":"0.85","criticality":"12.0","sat_point":"0.025362685130688498","system_utility":"2256960.7635999564","adt":"1.1140162078221107","shop_utility":"275505.2129059975","uid":"_YlC9NvdzEeyJ463rwa3DNQ","connectivity":"2.0","provided_interface":"1"},"Persistence Service":{"component_utility":"0.0","required_interface":"0","request":"59.0","replica":"4.0","failure_name":"None","perf_max":"19.811111463712113","importance":"20.0","reliability":"0.5","criticality":"15.0","sat_point":"0.057073226231168075","system_utility":"2256960.7635999564","adt":"1.4197860282259218","shop_utility":"275505.2129059975","uid":"_YlC9S_dzEeyJ463rwa3DNQ","connectivity":"1.0","provided_interface":"1"},"Item Management Service":{"component_utility":"0.0","required_interface":"4","request":"485.0","replica":"27.0","failure_name":"None","perf_max":"18.45743490537749","importance":"20.0","reliability":"0.5","criticality":"12.0","sat_point":"0.05536998694174035","system_utility":"2256960.7635999564","adt":"1.4447194569945707","shop_utility":"275505.2129059975","uid":"_YlC9L_dzEeyJ463rwa3DNQ","connectivity":"6.0","provided_interface":"2"},"Buy Now Item Filter":{"component_utility":"0.0","required_interface":"1","request":"285.0","replica":"10.0","failure_name":"None","perf_max":"6.572020387423819","importance":"20.0","reliability":"0.5","criticality":"13.0","sat_point":"0.03223010259249852","system_utility":"2256960.7635999564","adt":"1.264583967805634","shop_utility":"275505.2129059975","uid":"_YlC9XPdzEeyJ463rwa3DNQ","connectivity":"2.0","provided_interface":"1"},"Query Service":{"component_utility":"0.0","required_interface":"1","request":"469.0","replica":"12.0","failure_name":"None","perf_max":"15.638260292962235","importance":"20.0","reliability":"0.5","criticality":"29.0","sat_point":"0.025129626474919963","system_utility":"2256960.7635999564","adt":"1.453799123360215","shop_utility":"275505.2129059975","uid":"_YlC9TfdzEeyJ463rwa3DNQ","connectivity":"3.0","provided_interface":"2"},"Past Sales Item Filter":{"component_utility":"0.0","required_interface":"1","request":"135.0","replica":"6.0","failure_name":"None","perf_max":"18.788007171213202","importance":"20.0","reliability":"0.5","criticality":"17.0","sat_point":"0.04282965622198201","system_utility":"2256960.7635999564","adt":"1.286415600816538","shop_utility":"275505.2129059975","uid":"_YlC9V_dzEeyJ463rwa3DNQ","connectivity":"2.0","provided_interface":"1"},"Inventory Service":{"component_utility":"0.0","required_interface":"2","request":"317.0","replica":"10.0","failure_name":"None","perf_max":"10.234438874519249","importance":"20.0","reliability":"0.5","criticality":"22.0","sat_point":"0.030309544699775835","system_utility":"2256960.7635999564","adt":"1.3513834692621245","shop_utility":"275505.2129059975","uid":"_YlC9QfdzEeyJ463rwa3DNQ","connectivity":"3.0","provided_interface":"1"},"Region Item Filter":{"component_utility":"0.0","required_interface":"1","request":"189.0","replica":"6.0","failure_name":"None","perf_max":"18.545001255145806","importance":"20.0","reliability":"0.5","criticality":"14.0","sat_point":"0.031169668271633928","system_utility":"2256960.7635999564","adt":"1.3459570756297095","shop_utility":"275505.2129059975","uid":"_YlC9ZvdzEeyJ463rwa3DNQ","connectivity":"2.0","provided_interface":"1"},"Category Item Filter":{"component_utility":"0.0","required_interface":"1","request":"218.0","replica":"10.0","failure_name":"None","perf_max":"7.311837387771401","importance":"20.0","reliability":"0.5","criticality":"19.0","sat_point":"0.042225913491143234","system_utility":"2256960.7635999564","adt":"1.0284556584050808","shop_utility":"275505.2129059975","uid":"_YlC9d_dzEeyJ463rwa3DNQ","connectivity":"2.0","provided_interface":"1"},"Last Second Sales Item Filter":{"component_utility":"0.0","required_interface":"1","request":"375.0","replica":"21.0","failure_name":"None","perf_max":"13.387214882587912","importance":"20.0","reliability":"0.5","criticality":"25.0","sat_point":"0.05409054030995984","system_utility":"2256960.7635999564","adt":"1.1762964360044588","shop_utility":"275505.2129059975","uid":"_YlC9UfdzEeyJ463rwa3DNQ","connectivity":"2.0","provided_interface":"1"},"Future Sales Item Filter":{"component_utility":"0.0","required_interface":"1","request":"406.0","replica":"23.0","failure_name":"None","perf_max":"7.88766258577082","importance":"20.0","reliability":"0.5","criticality":"17.0","sat_point":"0.055229794880713085","system_utility":"2256960.7635999564","adt":"1.1314745345882298","shop_utility":"275505.2129059975","uid":"_YlC9gvdzEeyJ463rwa3DNQ","connectivity":"2.0","provided_interface":"1"}},"mRUBiS #5":{"Availability Item Filter":{"component_utility":"10201.508282716091","required_interface":"1","request":"318.0","replica":"8.0","failure_name":"None","perf_max":"15.202819009833096","importance":"12.0","reliability":"0.5","criticality":"28.0","sat_point":"0.022570903086534536","system_utility":"2256960.7635999564","adt":"1.4786091891751194","shop_utility":"165219.09304954487","uid":"_YlC8wfdzEeyJ463rwa3DNQ","connectivity":"2.0","provided_interface":"1"},"Bid and Buy Service":{"component_utility":"10066.64751863559","required_interface":"5","request":"427.0","replica":"20.0","failure_name":"None","perf_max":"10.770027992759006","importance":"12.0","reliability":"0.5","criticality":"26.0","sat_point":"0.04465305064730373","system_utility":"2256960.7635999564","adt":"1.4098682586842224","shop_utility":"165219.09304954487","uid":"_YlC8mfdzEeyJ463rwa3DNQ","connectivity":"7.0","provided_interface":"2"},"Seller Reputation Item Filter":{"component_utility":"3056.473244673996","required_interface":"1","request":"455.0","replica":"28.0","failure_name":"None","perf_max":"7.517502967608486","importance":"12.0","reliability":"0.5","criticality":"17.0","sat_point":"0.059890151450378404","system_utility":"2256960.7635999564","adt":"1.0667966110266798","shop_utility":"165219.09304954487","uid":"_YlC8y_dzEeyJ463rwa3DNQ","connectivity":"2.0","provided_interface":"1"},"User Management Service":{"component_utility":"4845.775171011221","required_interface":"4","request":"410.0","replica":"23.0","failure_name":"None","perf_max":"14.718096625108391","importance":"12.0","reliability":"0.5","criticality":"11.0","sat_point":"0.05591157017622139","system_utility":"2256960.7635999564","adt":"1.1196715274547957","shop_utility":"165219.09304954487","uid":"_YlC8hfdzEeyJ463rwa3DNQ","connectivity":"8.0","provided_interface":"4"},"Reputation Service":{"component_utility":"8613.375232956852","required_interface":"4","request":"385.0","replica":"19.0","failure_name":"None","perf_max":"10.266424585632524","importance":"12.0","reliability":"0.5","criticality":"28.0","sat_point":"0.04738655840883044","system_utility":"2256960.7635999564","adt":"1.042141897446748","shop_utility":"165219.09304954487","uid":"_YlC8pfdzEeyJ463rwa3DNQ","connectivity":"5.0","provided_interface":"1"},"Comment Item Filter":{"component_utility":"6538.572414067782","required_interface":"1","request":"103.0","replica":"4.0","failure_name":"None","perf_max":"10.106530011534034","importance":"12.0","reliability":"0.5","criticality":"27.0","sat_point":"0.032603735506591465","system_utility":"2256960.7635999564","adt":"1.0459033406272709","shop_utility":"165219.09304954487","uid":"_YlC80fdzEeyJ463rwa3DNQ","connectivity":"2.0","provided_interface":"1"},"Recommendation Item Filter":{"component_utility":"5329.0318052396115","required_interface":"1","request":"304.0","replica":"8.0","failure_name":"None","perf_max":"15.902749437653803","importance":"12.0","reliability":"0.5","criticality":"14.0","sat_point":"0.02486007911765469","system_utility":"2256960.7635999564","adt":"1.429200581206582","shop_utility":"165219.09304954487","uid":"_YlC83fdzEeyJ463rwa3DNQ","connectivity":"2.0","provided_interface":"1"},"Authentication Service":{"component_utility":"8073.7844508686285","required_interface":"1","request":"476.0","replica":"13.0","failure_name":"None","perf_max":"8.256032202080931","importance":"12.0","reliability":"0.85","criticality":"12.0","sat_point":"0.025362685130688498","system_utility":"2256960.7635999564","adt":"1.0522281409017928","shop_utility":"165219.09304954487","uid":"_YlC8lvdzEeyJ463rwa3DNQ","connectivity":"2.0","provided_interface":"1"},"Persistence Service":{"component_utility":"8901.06937562774","required_interface":"0","request":"480.0","replica":"28.0","failure_name":"None","perf_max":"19.811111463712113","importance":"12.0","reliability":"0.5","criticality":"15.0","sat_point":"0.057073226231168075","system_utility":"2256960.7635999564","adt":"1.3930783042710448","shop_utility":"165219.09304954487","uid":"_YlC8q_dzEeyJ463rwa3DNQ","connectivity":"1.0","provided_interface":"1"},"Item Management Service":{"component_utility":"6633.7080035531035","required_interface":"4","request":"419.0","replica":"24.0","failure_name":"None","perf_max":"18.45743490537749","importance":"12.0","reliability":"0.5","criticality":"12.0","sat_point":"0.05536998694174035","system_utility":"2256960.7635999564","adt":"1.0968562382793103","shop_utility":"165219.09304954487","uid":"_YlC8j_dzEeyJ463rwa3DNQ","connectivity":"6.0","provided_interface":"2"},"Buy Now Item Filter":{"component_utility":"2040.090705645144","required_interface":"1","request":"240.0","replica":"8.0","failure_name":"None","perf_max":"6.572020387423819","importance":"12.0","reliability":"0.5","criticality":"13.0","sat_point":"0.03223010259249852","system_utility":"2256960.7635999564","adt":"1.0379655231087448","shop_utility":"165219.09304954487","uid":"_YlC8vPdzEeyJ463rwa3DNQ","connectivity":"2.0","provided_interface":"1"},"Query Service":{"component_utility":"54407.2141523087","required_interface":"1","request":"281.0","replica":"8.0","failure_name":"None","perf_max":"15.638260292962235","importance":"12.0","reliability":"0.5","criticality":"29.0","sat_point":"0.025129626474919963","system_utility":"2256960.7635999564","adt":"1.3931667199892024","shop_utility":"165219.09304954487","uid":"_YlC8rfdzEeyJ463rwa3DNQ","connectivity":"3.0","provided_interface":"2"},"Past Sales Item Filter":{"component_utility":"7653.3220651920665","required_interface":"1","request":"179.0","replica":"8.0","failure_name":"None","perf_max":"18.788007171213202","importance":"12.0","reliability":"0.5","criticality":"17.0","sat_point":"0.04282965622198201","system_utility":"2256960.7635999564","adt":"1.218486066292019","shop_utility":"165219.09304954487","uid":"_YlC8t_dzEeyJ463rwa3DNQ","connectivity":"2.0","provided_interface":"1"},"Inventory Service":{"component_utility":"8094.184552384184","required_interface":"2","request":"373.0","replica":"12.0","failure_name":"None","perf_max":"10.234438874519249","importance":"12.0","reliability":"0.5","criticality":"22.0","sat_point":"0.030309544699775835","system_utility":"2256960.7635999564","adt":"1.1491036235060772","shop_utility":"165219.09304954487","uid":"_YlC8ofdzEeyJ463rwa3DNQ","connectivity":"3.0","provided_interface":"1"},"Region Item Filter":{"component_utility":"6216.727227118525","required_interface":"1","request":"184.0","replica":"6.0","failure_name":"None","perf_max":"18.545001255145806","importance":"12.0","reliability":"0.5","criticality":"14.0","sat_point":"0.031169668271633928","system_utility":"2256960.7635999564","adt":"1.4393194610466697","shop_utility":"165219.09304954487","uid":"_YlC8xvdzEeyJ463rwa3DNQ","connectivity":"2.0","provided_interface":"1"},"Category Item Filter":{"component_utility":"3322.4798720490803","required_interface":"1","request":"127.0","replica":"6.0","failure_name":"None","perf_max":"7.311837387771401","importance":"12.0","reliability":"0.5","criticality":"19.0","sat_point":"0.042225913491143234","system_utility":"2256960.7635999564","adt":"1.1717976774678758","shop_utility":"165219.09304954487","uid":"_YlC81_dzEeyJ463rwa3DNQ","connectivity":"2.0","provided_interface":"1"},"Last Second Sales Item Filter":{"component_utility":"8021.015913001785","required_interface":"1","request":"327.0","replica":"18.0","failure_name":"None","perf_max":"13.387214882587912","importance":"12.0","reliability":"0.5","criticality":"25.0","sat_point":"0.05409054030995984","system_utility":"2256960.7635999564","adt":"1.1313016550962014","shop_utility":"165219.09304954487","uid":"_YlC8sfdzEeyJ463rwa3DNQ","connectivity":"2.0","provided_interface":"1"},"Future Sales Item Filter":{"component_utility":"3204.1130624947345","required_interface":"1","request":"321.0","replica":"18.0","failure_name":"None","perf_max":"7.88766258577082","importance":"12.0","reliability":"0.5","criticality":"17.0","sat_point":"0.055229794880713085","system_utility":"2256960.7635999564","adt":"1.4053272499760079","shop_utility":"165219.09304954487","uid":"_YlC84vdzEeyJ463rwa3DNQ","connectivity":"2.0","provided_interface":"1"}},"mRUBiS #4":{"Availability Item Filter":{"component_utility":"0.0","required_interface":"1","request":"237.0","replica":"6.0","failure_name":"None","perf_max":"15.202819009833096","importance":"13.0","reliability":"0.5","criticality":"28.0","sat_point":"0.022570903086534536","system_utility":"2256960.7635999564","adt":"1.2790267295521829","shop_utility":"179004.5463312182","uid":"_YlC8IfdzEeyJ463rwa3DNQ","connectivity":"2.0","provided_interface":"1"},"Bid and Buy Service":{"component_utility":"0.0","required_interface":"5","request":"444.0","replica":"20.0","failure_name":"None","perf_max":"10.770027992759006","importance":"13.0","reliability":"0.5","criticality":"26.0","sat_point":"0.04465305064730373","system_utility":"2256960.7635999564","adt":"1.0665085877375362","shop_utility":"179004.5463312182","uid":"_YlC7-fdzEeyJ463rwa3DNQ","connectivity":"7.0","provided_interface":"2"},"Seller Reputation Item Filter":{"component_utility":"0.0","required_interface":"1","request":"123.0","replica":"8.0","failure_name":"None","perf_max":"7.517502967608486","importance":"13.0","reliability":"0.5","criticality":"17.0","sat_point":"0.059890151450378404","system_utility":"2256960.7635999564","adt":"1.2306364625121993","shop_utility":"179004.5463312182","uid":"_YlC8K_dzEeyJ463rwa3DNQ","connectivity":"2.0","provided_interface":"1"},"User Management Service":{"component_utility":"0.0","required_interface":"4","request":"59.0","replica":"4.0","failure_name":"None","perf_max":"14.718096625108391","importance":"13.0","reliability":"0.5","criticality":"11.0","sat_point":"0.05591157017622139","system_utility":"2256960.7635999564","adt":"1.0718065939571828","shop_utility":"179004.5463312182","uid":"_YlC75fdzEeyJ463rwa3DNQ","connectivity":"8.0","provided_interface":"4"},"Reputation Service":{"component_utility":"0.0","required_interface":"4","request":"51.0","replica":"3.0","failure_name":"None","perf_max":"10.266424585632524","importance":"13.0","reliability":"0.5","criticality":"28.0","sat_point":"0.04738655840883044","system_utility":"2256960.7635999564","adt":"1.0217241114227846","shop_utility":"179004.5463312182","uid":"_YlC8BfdzEeyJ463rwa3DNQ","connectivity":"5.0","provided_interface":"1"},"Comment Item Filter":{"component_utility":"0.0","required_interface":"1","request":"275.0","replica":"9.0","failure_name":"None","perf_max":"10.106530011534034","importance":"13.0","reliability":"0.5","criticality":"27.0","sat_point":"0.032603735506591465","system_utility":"2256960.7635999564","adt":"1.0085112214003025","shop_utility":"179004.5463312182","uid":"_YlC8MfdzEeyJ463rwa3DNQ","connectivity":"2.0","provided_interface":"1"},"Recommendation Item Filter":{"component_utility":"5776.733371616831","required_interface":"1","request":"381.0","replica":"10.0","failure_name":"None","perf_max":"15.902749437653803","importance":"13.0","reliability":"0.5","criticality":"14.0","sat_point":"0.02486007911765469","system_utility":"2256960.7635999564","adt":"1.1867423689153254","shop_utility":"179004.5463312182","uid":"_YlC8PfdzEeyJ463rwa3DNQ","root_issue":"true","connectivity":"2.0","provided_interface":"1"},"Authentication Service":{"component_utility":"0.0","required_interface":"1","request":"346.0","replica":"9.0","failure_name":"None","perf_max":"8.256032202080931","importance":"13.0","reliability":"0.85","criticality":"12.0","sat_point":"0.025362685130688498","system_utility":"2256960.7635999564","adt":"1.2205294098858512","shop_utility":"179004.5463312182","uid":"_YlC79vdzEeyJ463rwa3DNQ","connectivity":"2.0","provided_interface":"1"},"Persistence Service":{"component_utility":"0.0","required_interface":"0","request":"78.0","replica":"5.0","failure_name":"None","perf_max":"19.811111463712113","importance":"13.0","reliability":"0.5","criticality":"15.0","sat_point":"0.057073226231168075","system_utility":"2256960.7635999564","adt":"1.4731849649404387","shop_utility":"179004.5463312182","uid":"_YlC8C_dzEeyJ463rwa3DNQ","connectivity":"1.0","provided_interface":"1"},"Item Management Service":{"component_utility":"0.0","required_interface":"4","request":"97.0","replica":"6.0","failure_name":"None","perf_max":"18.45743490537749","importance":"13.0","reliability":"0.5","criticality":"12.0","sat_point":"0.05536998694174035","system_utility":"2256960.7635999564","adt":"1.4229676562052787","shop_utility":"179004.5463312182","uid":"_YlC77_dzEeyJ463rwa3DNQ","connectivity":"6.0","provided_interface":"2"},"Buy Now Item Filter":{"component_utility":"0.0","required_interface":"1","request":"354.0","replica":"12.0","failure_name":"None","perf_max":"6.572020387423819","importance":"13.0","reliability":"0.5","criticality":"13.0","sat_point":"0.03223010259249852","system_utility":"2256960.7635999564","adt":"1.1209054437079475","shop_utility":"179004.5463312182","uid":"_YlC8HPdzEeyJ463rwa3DNQ","connectivity":"2.0","provided_interface":"1"},"Query Service":{"component_utility":"0.0","required_interface":"1","request":"299.0","replica":"8.0","failure_name":"None","perf_max":"15.638260292962235","importance":"13.0","reliability":"0.5","criticality":"29.0","sat_point":"0.025129626474919963","system_utility":"2256960.7635999564","adt":"1.4822577399287327","shop_utility":"179004.5463312182","uid":"_YlC8DfdzEeyJ463rwa3DNQ","connectivity":"3.0","provided_interface":"2"},"Past Sales Item Filter":{"component_utility":"0.0","required_interface":"1","request":"125.0","replica":"6.0","failure_name":"None","perf_max":"18.788007171213202","importance":"13.0","reliability":"0.5","criticality":"17.0","sat_point":"0.04282965622198201","system_utility":"2256960.7635999564","adt":"1.3517697019381396","shop_utility":"179004.5463312182","uid":"_YlC8F_dzEeyJ463rwa3DNQ","connectivity":"2.0","provided_interface":"1"},"Inventory Service":{"component_utility":"0.0","required_interface":"2","request":"378.0","replica":"12.0","failure_name":"None","perf_max":"10.234438874519249","importance":"13.0","reliability":"0.5","criticality":"22.0","sat_point":"0.030309544699775835","system_utility":"2256960.7635999564","adt":"1.3142680106808196","shop_utility":"179004.5463312182","uid":"_YlC8AfdzEeyJ463rwa3DNQ","connectivity":"3.0","provided_interface":"1"},"Region Item Filter":{"component_utility":"0.0","required_interface":"1","request":"472.0","replica":"15.0","failure_name":"None","perf_max":"18.545001255145806","importance":"13.0","reliability":"0.5","criticality":"14.0","sat_point":"0.031169668271633928","system_utility":"2256960.7635999564","adt":"1.2670189856575245","shop_utility":"179004.5463312182","uid":"_YlC8JvdzEeyJ463rwa3DNQ","connectivity":"2.0","provided_interface":"1"},"Category Item Filter":{"component_utility":"0.0","required_interface":"1","request":"54.0","replica":"3.0","failure_name":"None","perf_max":"7.311837387771401","importance":"13.0","reliability":"0.5","criticality":"19.0","sat_point":"0.042225913491143234","system_utility":"2256960.7635999564","adt":"1.3336253929899","shop_utility":"179004.5463312182","uid":"_YlC8N_dzEeyJ463rwa3DNQ","connectivity":"2.0","provided_interface":"1"},"Last Second Sales Item Filter":{"component_utility":"0.0","required_interface":"1","request":"435.0","replica":"24.0","failure_name":"None","perf_max":"13.387214882587912","importance":"13.0","reliability":"0.5","criticality":"25.0","sat_point":"0.05409054030995984","system_utility":"2256960.7635999564","adt":"1.2599169524584708","shop_utility":"179004.5463312182","uid":"_YlC8EfdzEeyJ463rwa3DNQ","connectivity":"2.0","provided_interface":"1"},"Future Sales Item Filter":{"component_utility":"0.0","required_interface":"1","request":"449.0","replica":"25.0","failure_name":"None","perf_max":"7.88766258577082","importance":"13.0","reliability":"0.5","criticality":"17.0","sat_point":"0.055229794880713085","system_utility":"2256960.7635999564","adt":"1.0899374826614352","shop_utility":"179004.5463312182","uid":"_YlC8QvdzEeyJ463rwa3DNQ","connectivity":"2.0","provided_interface":"1"}},"mRUBiS #3":{"Availability Item Filter":{"component_utility":"13607.659890523499","required_interface":"1","request":"73.0","replica":"2.0","failure_name":"None","perf_max":"15.202819009833096","importance":"16.0","reliability":"0.5","criticality":"28.0","sat_point":"0.022570903086534536","system_utility":"2256960.7635999564","adt":"1.4065942286956654","shop_utility":"220367.06980534297","uid":"_YlC7gfdzEeyJ463rwa3DNQ","connectivity":"2.0","provided_interface":"1"},"Bid and Buy Service":{"component_utility":"13427.826156075853","required_interface":"5","request":"412.0","replica":"19.0","failure_name":"None","perf_max":"10.770027992759006","importance":"16.0","reliability":"0.5","criticality":"26.0","sat_point":"0.04465305064730373","system_utility":"2256960.7635999564","adt":"1.3168778887388173","shop_utility":"220367.06980534297","uid":"_YlC7WfdzEeyJ463rwa3DNQ","connectivity":"7.0","provided_interface":"2"},"Seller Reputation Item Filter":{"component_utility":"4075.0052961137653","required_interface":"1","request":"477.0","replica":"29.0","failure_name":"None","perf_max":"7.517502967608486","importance":"16.0","reliability":"0.5","criticality":"17.0","sat_point":"0.059890151450378404","system_utility":"2256960.7635999564","adt":"1.4516318265251213","shop_utility":"220367.06980534297","uid":"_YlC7i_dzEeyJ463rwa3DNQ","connectivity":"2.0","provided_interface":"1"},"User Management Service":{"component_utility":"6464.33631700672","required_interface":"4","request":"253.0","replica":"15.0","failure_name":"None","perf_max":"14.718096625108391","importance":"16.0","reliability":"0.5","criticality":"11.0","sat_point":"0.05591157017622139","system_utility":"2256960.7635999564","adt":"1.1626198040971776","shop_utility":"220367.06980534297","uid":"_YlC7RfdzEeyJ463rwa3DNQ","connectivity":"8.0","provided_interface":"4"},"Reputation Service":{"component_utility":"11484.342602212637","required_interface":"4","request":"500.0","replica":"24.0","failure_name":"None","perf_max":"10.266424585632524","importance":"16.0","reliability":"0.5","criticality":"28.0","sat_point":"0.04738655840883044","system_utility":"2256960.7635999564","adt":"1.4052933695791232","shop_utility":"220367.06980534297","uid":"_YlC7ZfdzEeyJ463rwa3DNQ","connectivity":"5.0","provided_interface":"1"},"Comment Item Filter":{"component_utility":"8718.194995500342","required_interface":"1","request":"175.0","replica":"6.0","failure_name":"None","perf_max":"10.106530011534034","importance":"16.0","reliability":"0.5","criticality":"27.0","sat_point":"0.032603735506591465","system_utility":"2256960.7635999564","adt":"1.3846934465063232","shop_utility":"220367.06980534297","uid":"_YlC7kfdzEeyJ463rwa3DNQ","connectivity":"2.0","provided_interface":"1"},"Recommendation Item Filter":{"component_utility":"7109.603638777889","required_interface":"1","request":"411.0","replica":"11.0","failure_name":"None","perf_max":"15.902749437653803","importance":"16.0","reliability":"0.5","criticality":"14.0","sat_point":"0.02486007911765469","system_utility":"2256960.7635999564","adt":"1.482810929101538","shop_utility":"220367.06980534297","uid":"_YlC7nfdzEeyJ463rwa3DNQ","connectivity":"2.0","provided_interface":"1"},"Authentication Service":{"component_utility":"10768.333381676655","required_interface":"1","request":"240.0","replica":"7.0","failure_name":"None","perf_max":"8.256032202080931","importance":"16.0","reliability":"0.85","criticality":"12.0","sat_point":"0.025362685130688498","system_utility":"2256960.7635999564","adt":"1.0742261360206935","shop_utility":"220367.06980534297","uid":"_YlC7VvdzEeyJ463rwa3DNQ","connectivity":"2.0","provided_interface":"1"},"Persistence Service":{"component_utility":"11874.183885317048","required_interface":"0","request":"451.0","replica":"26.0","failure_name":"None","perf_max":"19.811111463712113","importance":"16.0","reliability":"0.5","criticality":"15.0","sat_point":"0.057073226231168075","system_utility":"2256960.7635999564","adt":"1.2482992910219157","shop_utility":"220367.06980534297","uid":"_YlC7a_dzEeyJ463rwa3DNQ","connectivity":"1.0","provided_interface":"1"},"Item Management Service":{"component_utility":"8849.067387560059","required_interface":"4","request":"416.0","replica":"24.0","failure_name":"None","perf_max":"18.45743490537749","importance":"16.0","reliability":"0.5","criticality":"12.0","sat_point":"0.05536998694174035","system_utility":"2256960.7635999564","adt":"1.0501367021136003","shop_utility":"220367.06980534297","uid":"_YlC7T_dzEeyJ463rwa3DNQ","connectivity":"6.0","provided_interface":"2"},"Buy Now Item Filter":{"component_utility":"2723.936409590459","required_interface":"1","request":"232.0","replica":"8.0","failure_name":"None","perf_max":"6.572020387423819","importance":"16.0","reliability":"0.5","criticality":"13.0","sat_point":"0.03223010259249852","system_utility":"2256960.7635999564","adt":"1.0024071577849862","shop_utility":"220367.06980534297","uid":"_YlC7fPdzEeyJ463rwa3DNQ","connectivity":"2.0","provided_interface":"1"},"Query Service":{"component_utility":"72550.4739970717","required_interface":"1","request":"159.0","replica":"4.0","failure_name":"None","perf_max":"15.638260292962235","importance":"16.0","reliability":"0.5","criticality":"29.0","sat_point":"0.025129626474919963","system_utility":"2256960.7635999564","adt":"1.1053762273059253","shop_utility":"220367.06980534297","uid":"_YlC7bfdzEeyJ463rwa3DNQ","connectivity":"3.0","provided_interface":"2"},"Past Sales Item Filter":{"component_utility":"10210.003563020487","required_interface":"1","request":"285.0","replica":"13.0","failure_name":"None","perf_max":"18.788007171213202","importance":"16.0","reliability":"0.5","criticality":"17.0","sat_point":"0.04282965622198201","system_utility":"2256960.7635999564","adt":"1.067233811949594","shop_utility":"220367.06980534297","uid":"_YlC7d_dzEeyJ463rwa3DNQ","connectivity":"2.0","provided_interface":"1"},"Inventory Service":{"component_utility":"10797.469810143984","required_interface":"2","request":"155.0","replica":"5.0","failure_name":"None","perf_max":"10.234438874519249","importance":"16.0","reliability":"0.5","criticality":"22.0","sat_point":"0.030309544699775835","system_utility":"2256960.7635999564","adt":"1.0097641348341369","shop_utility":"220367.06980534297","uid":"_YlC7YfdzEeyJ463rwa3DNQ","connectivity":"3.0","provided_interface":"1"},"Region Item Filter":{"component_utility":"8296.122595454184","required_interface":"1","request":"148.0","replica":"5.0","failure_name":"None","perf_max":"18.545001255145806","importance":"16.0","reliability":"0.5","criticality":"14.0","sat_point":"0.031169668271633928","system_utility":"2256960.7635999564","adt":"1.2037966851137032","shop_utility":"220367.06980534297","uid":"_YlC7hvdzEeyJ463rwa3DNQ","connectivity":"2.0","provided_interface":"1"},"Category Item Filter":{"component_utility":"4432.992887450293","required_interface":"1","request":"276.0","replica":"12.0","failure_name":"None","perf_max":"7.311837387771401","importance":"16.0","reliability":"0.5","criticality":"19.0","sat_point":"0.042225913491143234","system_utility":"2256960.7635999564","adt":"1.260424431471903","shop_utility":"220367.06980534297","uid":"_YlC7l_dzEeyJ463rwa3DNQ","connectivity":"2.0","provided_interface":"1"},"Last Second Sales Item Filter":{"component_utility":"10698.479082880593","required_interface":"1","request":"130.0","replica":"8.0","failure_name":"None","perf_max":"13.387214882587912","importance":"16.0","reliability":"0.5","criticality":"25.0","sat_point":"0.05409054030995984","system_utility":"2256960.7635999564","adt":"1.129282318973751","shop_utility":"220367.06980534297","uid":"_YlC7cfdzEeyJ463rwa3DNQ","connectivity":"2.0","provided_interface":"1"},"Future Sales Item Filter":{"component_utility":"4279.037908966771","required_interface":"1","request":"143.0","replica":"8.0","failure_name":"None","perf_max":"7.88766258577082","importance":"16.0","reliability":"0.5","criticality":"17.0","sat_point":"0.055229794880713085","system_utility":"2256960.7635999564","adt":"1.1850537692554828","shop_utility":"220367.06980534297","uid":"_YlC7ovdzEeyJ463rwa3DNQ","connectivity":"2.0","provided_interface":"1"}},"mRUBiS #9":{"Availability Item Filter":{"component_utility":"0.0","required_interface":"1","request":"435.0","replica":"10.0","failure_name":"None","perf_max":"15.202819009833096","importance":"24.0","reliability":"0.5","criticality":"28.0","sat_point":"0.022570903086534536","system_utility":"2256960.7635999564","adt":"1.0822590661960407","shop_utility":"330644.7754950487","uid":"_YlDhavdzEeyJ463rwa3DNQ","connectivity":"2.0","provided_interface":"1"},"Bid and Buy Service":{"component_utility":"0.0","required_interface":"5","request":"52.0","replica":"3.0","failure_name":"None","perf_max":"10.770027992759006","importance":"24.0","reliability":"0.5","criticality":"26.0","sat_point":"0.04465305064730373","system_utility":"2256960.7635999564","adt":"1.4641572869571016","shop_utility":"330644.7754950487","uid":"_YlDhQvdzEeyJ463rwa3DNQ","connectivity":"7.0","provided_interface":"2"},"Seller Reputation Item Filter":{"component_utility":"0.0","required_interface":"1","request":"187.0","replica":"12.0","failure_name":"None","perf_max":"7.517502967608486","importance":"24.0","reliability":"0.5","criticality":"17.0","sat_point":"0.059890151450378404","system_utility":"2256960.7635999564","adt":"1.2396999850659876","shop_utility":"330644.7754950487","uid":"_YlDhdPdzEeyJ463rwa3DNQ","connectivity":"2.0","provided_interface":"1"},"User Management Service":{"component_utility":"0.0","required_interface":"4","request":"415.0","replica":"24.0","failure_name":"None","perf_max":"14.718096625108391","importance":"24.0","reliability":"0.5","criticality":"11.0","sat_point":"0.05591157017622139","system_utility":"2256960.7635999564","adt":"1.3449927521513771","shop_utility":"330644.7754950487","uid":"_YlDhLvdzEeyJ463rwa3DNQ","connectivity":"8.0","provided_interface":"4"},"Reputation Service":{"component_utility":"0.0","required_interface":"4","request":"462.0","replica":"22.0","failure_name":"None","perf_max":"10.266424585632524","importance":"24.0","reliability":"0.5","criticality":"28.0","sat_point":"0.04738655840883044","system_utility":"2256960.7635999564","adt":"1.47651411325009","shop_utility":"330644.7754950487","uid":"_YlDhTvdzEeyJ463rwa3DNQ","connectivity":"5.0","provided_interface":"1"},"Comment Item Filter":{"component_utility":"0.0","required_interface":"1","request":"419.0","replica":"14.0","failure_name":"None","perf_max":"10.106530011534034","importance":"24.0","reliability":"0.5","criticality":"27.0","sat_point":"0.032603735506591465","system_utility":"2256960.7635999564","adt":"1.3376494766399245","shop_utility":"330644.7754950487","uid":"_YlDhevdzEeyJ463rwa3DNQ","connectivity":"2.0","provided_interface":"1"},"Recommendation Item Filter":{"component_utility":"0.0","required_interface":"1","request":"100.0","replica":"3.0","failure_name":"None","perf_max":"15.902749437653803","importance":"24.0","reliability":"0.5","criticality":"14.0","sat_point":"0.02486007911765469","system_utility":"2256960.7635999564","adt":"1.4820898465714238","shop_utility":"330644.7754950487","uid":"_YlDhhvdzEeyJ463rwa3DNQ","connectivity":"2.0","provided_interface":"1"},"Authentication Service":{"component_utility":"0.0","required_interface":"1","request":"283.0","replica":"8.0","failure_name":"None","perf_max":"8.256032202080931","importance":"24.0","reliability":"0.85","criticality":"12.0","sat_point":"0.025362685130688498","system_utility":"2256960.7635999564","adt":"1.4456442730834596","shop_utility":"330644.7754950487","uid":"_YlDhP_dzEeyJ463rwa3DNQ","connectivity":"2.0","provided_interface":"1"},"Persistence Service":{"component_utility":"0.0","required_interface":"0","request":"91.0","replica":"6.0","failure_name":"None","perf_max":"19.811111463712113","importance":"24.0","reliability":"0.5","criticality":"15.0","sat_point":"0.057073226231168075","system_utility":"2256960.7635999564","adt":"1.298628054634989","shop_utility":"330644.7754950487","uid":"_YlDhVPdzEeyJ463rwa3DNQ","connectivity":"1.0","provided_interface":"1"},"Item Management Service":{"component_utility":"0.0","required_interface":"4","request":"270.0","replica":"15.0","failure_name":"None","perf_max":"18.45743490537749","importance":"24.0","reliability":"0.5","criticality":"12.0","sat_point":"0.05536998694174035","system_utility":"2256960.7635999564","adt":"1.4047769287802607","shop_utility":"330644.7754950487","uid":"_YlDhOPdzEeyJ463rwa3DNQ","connectivity":"6.0","provided_interface":"2"},"Buy Now Item Filter":{"component_utility":"0.0","required_interface":"1","request":"217.0","replica":"7.0","failure_name":"None","perf_max":"6.572020387423819","importance":"24.0","reliability":"0.5","criticality":"13.0","sat_point":"0.03223010259249852","system_utility":"2256960.7635999564","adt":"1.070778113441398","shop_utility":"330644.7754950487","uid":"_YlDhZfdzEeyJ463rwa3DNQ","connectivity":"2.0","provided_interface":"1"},"Query Service":{"component_utility":"0.0","required_interface":"1","request":"245.0","replica":"7.0","failure_name":"None","perf_max":"15.638260292962235","importance":"24.0","reliability":"0.5","criticality":"29.0","sat_point":"0.025129626474919963","system_utility":"2256960.7635999564","adt":"1.281534167907447","shop_utility":"330644.7754950487","uid":"_YlDhVvdzEeyJ463rwa3DNQ","connectivity":"3.0","provided_interface":"2"},"Past Sales Item Filter":{"component_utility":"15318.402332696849","required_interface":"1","request":"241.0","replica":"11.0","failure_name":"None","perf_max":"18.788007171213202","importance":"24.0","reliability":"0.5","criticality":"17.0","sat_point":"0.04282965622198201","system_utility":"2256960.7635999564","adt":"1.2611519013124706","shop_utility":"330644.7754950487","uid":"_YlDhYPdzEeyJ463rwa3DNQ","root_issue":"true","connectivity":"2.0","provided_interface":"1"},"Inventory Service":{"component_utility":"0.0","required_interface":"2","request":"141.0","replica":"5.0","failure_name":"None","perf_max":"10.234438874519249","importance":"24.0","reliability":"0.5","criticality":"22.0","sat_point":"0.030309544699775835","system_utility":"2256960.7635999564","adt":"1.2975359787784282","shop_utility":"330644.7754950487","uid":"_YlDhSvdzEeyJ463rwa3DNQ","connectivity":"3.0","provided_interface":"1"},"Region Item Filter":{"component_utility":"0.0","required_interface":"1","request":"451.0","replica":"15.0","failure_name":"None","perf_max":"18.545001255145806","importance":"24.0","reliability":"0.5","criticality":"14.0","sat_point":"0.031169668271633928","system_utility":"2256960.7635999564","adt":"1.2886965436832833","shop_utility":"330644.7754950487","uid":"_YlDhb_dzEeyJ463rwa3DNQ","connectivity":"2.0","provided_interface":"1"},"Category Item Filter":{"component_utility":"0.0","required_interface":"1","request":"497.0","replica":"21.0","failure_name":"None","perf_max":"7.311837387771401","importance":"24.0","reliability":"0.5","criticality":"19.0","sat_point":"0.042225913491143234","system_utility":"2256960.7635999564","adt":"1.4993739267345076","shop_utility":"330644.7754950487","uid":"_YlDhgPdzEeyJ463rwa3DNQ","connectivity":"2.0","provided_interface":"1"},"Last Second Sales Item Filter":{"component_utility":"0.0","required_interface":"1","request":"368.0","replica":"20.0","failure_name":"None","perf_max":"13.387214882587912","importance":"24.0","reliability":"0.5","criticality":"25.0","sat_point":"0.05409054030995984","system_utility":"2256960.7635999564","adt":"1.0693283699534917","shop_utility":"330644.7754950487","uid":"_YlDhWvdzEeyJ463rwa3DNQ","connectivity":"2.0","provided_interface":"1"},"Future Sales Item Filter":{"component_utility":"0.0","required_interface":"1","request":"100.0","replica":"6.0","failure_name":"None","perf_max":"7.88766258577082","importance":"24.0","reliability":"0.5","criticality":"17.0","sat_point":"0.055229794880713085","system_utility":"2256960.7635999564","adt":"1.1578937500611022","shop_utility":"330644.7754950487","uid":"_YlDhi_dzEeyJ463rwa3DNQ","connectivity":"2.0","provided_interface":"1"}},"mRUBiS #8":{"Availability Item Filter":{"component_utility":"1538.709988357943","required_interface":"1","request":"261.0","replica":"6.0","failure_name":"None","perf_max":"15.202819009833096","importance":"17.0","reliability":"0.5","criticality":"28.0","sat_point":"0.022570903086534536","system_utility":"2256960.7635999564","adt":"1.0373709003163771","shop_utility":"173635.5299541081","uid":"_YlDgyvdzEeyJ463rwa3DNQ","connectivity":"2.0","provided_interface":"1"},"Bid and Buy Service":{"component_utility":"14166.079314659175","required_interface":"5","request":"456.0","replica":"21.0","failure_name":"None","perf_max":"10.770027992759006","importance":"17.0","reliability":"0.5","criticality":"26.0","sat_point":"0.04465305064730373","system_utility":"2256960.7635999564","adt":"1.4977803739268598","shop_utility":"173635.5299541081","uid":"_YlDgovdzEeyJ463rwa3DNQ","connectivity":"7.0","provided_interface":"2"},"Seller Reputation Item Filter":{"component_utility":"4275.536326317333","required_interface":"1","request":"181.0","replica":"11.0","failure_name":"None","perf_max":"7.517502967608486","importance":"17.0","reliability":"0.5","criticality":"17.0","sat_point":"0.059890151450378404","system_utility":"2256960.7635999564","adt":"1.2580388960372537","shop_utility":"173635.5299541081","uid":"_YlDg1PdzEeyJ463rwa3DNQ","connectivity":"2.0","provided_interface":"1"},"User Management Service":{"component_utility":"6460.641959881209","required_interface":"4","request":"76.0","replica":"5.0","failure_name":"None","perf_max":"14.718096625108391","importance":"17.0","reliability":"0.5","criticality":"11.0","sat_point":"0.05591157017622139","system_utility":"2256960.7635999564","adt":"1.2068212356963133","shop_utility":"173635.5299541081","uid":"_YlC-ZfdzEeyJ463rwa3DNQ","connectivity":"8.0","provided_interface":"4"},"Reputation Service":{"component_utility":"12204.755399740437","required_interface":"4","request":"97.0","replica":"5.0","failure_name":"None","perf_max":"10.266424585632524","importance":"17.0","reliability":"0.5","criticality":"28.0","sat_point":"0.04738655840883044","system_utility":"2256960.7635999564","adt":"1.2289857162266866","shop_utility":"173635.5299541081","uid":"_YlDgrvdzEeyJ463rwa3DNQ","connectivity":"5.0","provided_interface":"1"},"Comment Item Filter":{"component_utility":"9182.784741498173","required_interface":"1","request":"260.0","replica":"9.0","failure_name":"None","perf_max":"10.106530011534034","importance":"17.0","reliability":"0.5","criticality":"27.0","sat_point":"0.032603735506591465","system_utility":"2256960.7635999564","adt":"1.3009809090069462","shop_utility":"173635.5299541081","uid":"_YlDg2vdzEeyJ463rwa3DNQ","connectivity":"2.0","provided_interface":"1"},"Recommendation Item Filter":{"component_utility":"0.0","required_interface":"1","request":"149.0","replica":"4.0","failure_name":"CF3","perf_max":"15.902749437653803","importance":"17.0","reliability":"0.5","criticality":"14.0","sat_point":"0.02486007911765469","system_utility":"2256960.7635999564","adt":"1.1858046841163337","shop_utility":"173635.5299541081","uid":"_YlDg5vdzEeyJ463rwa3DNQ","root_issue":"true","connectivity":"2.0","provided_interface":"1"},"Authentication Service":{"component_utility":"11390.882313906068","required_interface":"1","request":"277.0","replica":"8.0","failure_name":"None","perf_max":"8.256032202080931","importance":"17.0","reliability":"0.85","criticality":"12.0","sat_point":"0.025362685130688498","system_utility":"2256960.7635999564","adt":"1.2885556820598927","shop_utility":"173635.5299541081","uid":"_YlDgn_dzEeyJ463rwa3DNQ","connectivity":"2.0","provided_interface":"1"},"Persistence Service":{"component_utility":"12617.408204617568","required_interface":"0","request":"135.0","replica":"8.0","failure_name":"None","perf_max":"19.811111463712113","importance":"17.0","reliability":"0.5","criticality":"15.0","sat_point":"0.057073226231168075","system_utility":"2256960.7635999564","adt":"1.017535349890366","shop_utility":"173635.5299541081","uid":"_YlDgtPdzEeyJ463rwa3DNQ","connectivity":"1.0","provided_interface":"1"},"Item Management Service":{"component_utility":"9398.37095279289","required_interface":"4","request":"328.0","replica":"19.0","failure_name":"None","perf_max":"18.45743490537749","importance":"17.0","reliability":"0.5","criticality":"12.0","sat_point":"0.05536998694174035","system_utility":"2256960.7635999564","adt":"1.4920848949630514","shop_utility":"173635.5299541081","uid":"_YlDgmPdzEeyJ463rwa3DNQ","connectivity":"6.0","provided_interface":"2"},"Buy Now Item Filter":{"component_utility":"2830.0312956263497","required_interface":"1","request":"408.0","replica":"14.0","failure_name":"None","perf_max":"6.572020387423819","importance":"17.0","reliability":"0.5","criticality":"13.0","sat_point":"0.03223010259249852","system_utility":"2256960.7635999564","adt":"1.4801715614978463","shop_utility":"173635.5299541081","uid":"_YlDgxfdzEeyJ463rwa3DNQ","connectivity":"2.0","provided_interface":"1"},"Query Service":{"component_utility":"76982.70198141469","required_interface":"1","request":"107.0","replica":"3.0","failure_name":"None","perf_max":"15.638260292962235","importance":"17.0","reliability":"0.5","criticality":"29.0","sat_point":"0.025129626474919963","system_utility":"2256960.7635999564","adt":"1.0921262889130143","shop_utility":"173635.5299541081","uid":"_YlDgtvdzEeyJ463rwa3DNQ","connectivity":"3.0","provided_interface":"2"},"Past Sales Item Filter":{"component_utility":"10844.61446464818","required_interface":"1","request":"191.0","replica":"9.0","failure_name":"None","perf_max":"18.788007171213202","importance":"17.0","reliability":"0.5","criticality":"17.0","sat_point":"0.04282965622198201","system_utility":"2256960.7635999564","adt":"1.4853680313050615","shop_utility":"173635.5299541081","uid":"_YlDgwPdzEeyJ463rwa3DNQ","connectivity":"2.0","provided_interface":"1"},"Inventory Service":{"component_utility":"-22011.12014972744","required_interface":"2","request":"325.0","replica":"10.0","failure_name":"None","perf_max":"10.234438874519249","importance":"17.0","reliability":"0.5","criticality":"22.0","sat_point":"0.030309544699775835","system_utility":"2256960.7635999564","adt":"1.3160566938040885","shop_utility":"173635.5299541081","uid":"_YlDgqvdzEeyJ463rwa3DNQ","connectivity":"3.0","provided_interface":"1"},"Region Item Filter":{"component_utility":"8668.191835655683","required_interface":"1","request":"339.0","replica":"11.0","failure_name":"None","perf_max":"18.545001255145806","importance":"17.0","reliability":"0.5","criticality":"14.0","sat_point":"0.031169668271633928","system_utility":"2256960.7635999564","adt":"1.0228761793721333","shop_utility":"173635.5299541081","uid":"_YlDgz_dzEeyJ463rwa3DNQ","connectivity":"2.0","provided_interface":"1"},"Category Item Filter":{"component_utility":"4561.81978157324","required_interface":"1","request":"367.0","replica":"16.0","failure_name":"None","perf_max":"7.311837387771401","importance":"17.0","reliability":"0.5","criticality":"19.0","sat_point":"0.042225913491143234","system_utility":"2256960.7635999564","adt":"1.1627170927085282","shop_utility":"173635.5299541081","uid":"_YlDg4PdzEeyJ463rwa3DNQ","connectivity":"2.0","provided_interface":"1"},"Last Second Sales Item Filter":{"component_utility":"11367.121543146644","required_interface":"1","request":"353.0","replica":"20.0","failure_name":"None","perf_max":"13.387214882587912","importance":"17.0","reliability":"0.5","criticality":"25.0","sat_point":"0.05409054030995984","system_utility":"2256960.7635999564","adt":"1.2011107053080303","shop_utility":"173635.5299541081","uid":"_YlDguvdzEeyJ463rwa3DNQ","connectivity":"2.0","provided_interface":"1"},"Future Sales Item Filter":{"component_utility":"-843.0","required_interface":"1","request":"59.0","replica":"4.0","failure_name":"CF3","perf_max":"7.88766258577082","importance":"17.0","reliability":"0.5","criticality":"17.0","sat_point":"0.055229794880713085","system_utility":"2256960.7635999564","adt":"1.3210433413498135","shop_utility":"173635.5299541081","uid":"_YlDg6_dzEeyJ463rwa3DNQ","connectivity":"2.0","provided_interface":"1"}},"mRUBiS #7":{"Availability Item Filter":{"component_utility":"13611.712189576001","required_interface":"1","request":"90.0","replica":"3.0","failure_name":"None","perf_max":"15.202819009833096","importance":"16.0","reliability":"0.5","criticality":"28.0","sat_point":"0.022570903086534536","system_utility":"2256960.7635999564","adt":"1.0013643234453444","shop_utility":"161157.9969575724","uid":"_YlC-AfdzEeyJ463rwa3DNQ","connectivity":"2.0","provided_interface":"1"},"Bid and Buy Service":{"component_utility":"13254.203173011812","required_interface":"5","request":"347.0","replica":"16.0","failure_name":"None","perf_max":"10.770027992759006","importance":"16.0","reliability":"0.5","criticality":"26.0","sat_point":"0.04465305064730373","system_utility":"2256960.7635999564","adt":"1.0791761951427445","shop_utility":"161157.9969575724","uid":"_YlC92fdzEeyJ463rwa3DNQ","connectivity":"7.0","provided_interface":"2"},"Seller Reputation Item Filter":{"component_utility":"1258.6264831724684","required_interface":"1","request":"405.0","replica":"25.0","failure_name":"None","perf_max":"7.517502967608486","importance":"16.0","reliability":"0.5","criticality":"17.0","sat_point":"0.059890151450378404","system_utility":"2256960.7635999564","adt":"1.1895131206548355","shop_utility":"161157.9969575724","uid":"_YlC-C_dzEeyJ463rwa3DNQ","connectivity":"2.0","provided_interface":"1"},"User Management Service":{"component_utility":"6165.997601518448","required_interface":"4","request":"298.0","replica":"17.0","failure_name":"None","perf_max":"14.718096625108391","importance":"16.0","reliability":"0.5","criticality":"11.0","sat_point":"0.05591157017622139","system_utility":"2256960.7635999564","adt":"1.3964913529243326","shop_utility":"161157.9969575724","uid":"_YlC9xfdzEeyJ463rwa3DNQ","connectivity":"8.0","provided_interface":"4"},"Reputation Service":{"component_utility":"10785.44820899052","required_interface":"4","request":"407.0","replica":"20.0","failure_name":"None","perf_max":"10.266424585632524","importance":"16.0","reliability":"0.5","criticality":"28.0","sat_point":"0.04738655840883044","system_utility":"2256960.7635999564","adt":"1.3947326917908802","shop_utility":"161157.9969575724","uid":"_YlC95fdzEeyJ463rwa3DNQ","connectivity":"5.0","provided_interface":"1"},"Comment Item Filter":{"component_utility":"8222.493119450839","required_interface":"1","request":"386.0","replica":"13.0","failure_name":"None","perf_max":"10.106530011534034","importance":"16.0","reliability":"0.5","criticality":"27.0","sat_point":"0.032603735506591465","system_utility":"2256960.7635999564","adt":"1.3548810514567118","shop_utility":"161157.9969575724","uid":"_YlC-EfdzEeyJ463rwa3DNQ","connectivity":"2.0","provided_interface":"1"},"Recommendation Item Filter":{"component_utility":"-13957.328389001925","required_interface":"1","request":"322.0","replica":"9.0","failure_name":"None","perf_max":"15.902749437653803","importance":"16.0","reliability":"0.5","criticality":"14.0","sat_point":"0.02486007911765469","system_utility":"2256960.7635999564","adt":"1.0760137070828555","shop_utility":"161157.9969575724","uid":"_YlC-HfdzEeyJ463rwa3DNQ","connectivity":"2.0","provided_interface":"1"},"Authentication Service":{"component_utility":"10648.783063813642","required_interface":"1","request":"339.0","replica":"9.0","failure_name":"None","perf_max":"8.256032202080931","importance":"16.0","reliability":"0.85","criticality":"12.0","sat_point":"0.025362685130688498","system_utility":"2256960.7635999564","adt":"1.429257922321963","shop_utility":"161157.9969575724","uid":"_YlC91vdzEeyJ463rwa3DNQ","connectivity":"2.0","provided_interface":"1"},"Persistence Service":{"component_utility":"11872.79463536494","required_interface":"0","request":"411.0","replica":"24.0","failure_name":"None","perf_max":"19.811111463712113","importance":"16.0","reliability":"0.5","criticality":"15.0","sat_point":"0.057073226231168075","system_utility":"2256960.7635999564","adt":"1.3872242862328623","shop_utility":"161157.9969575724","uid":"_YlC96_dzEeyJ463rwa3DNQ","connectivity":"1.0","provided_interface":"1"},"Item Management Service":{"component_utility":"8766.696258339343","required_interface":"4","request":"381.0","replica":"22.0","failure_name":"None","perf_max":"18.45743490537749","importance":"16.0","reliability":"0.5","criticality":"12.0","sat_point":"0.05536998694174035","system_utility":"2256960.7635999564","adt":"1.3872496241850454","shop_utility":"161157.9969575724","uid":"_YlC9z_dzEeyJ463rwa3DNQ","connectivity":"6.0","provided_interface":"2"},"Buy Now Item Filter":{"component_utility":"2516.5608545997875","required_interface":"1","request":"196.0","replica":"7.0","failure_name":"None","perf_max":"6.572020387423819","importance":"16.0","reliability":"0.5","criticality":"13.0","sat_point":"0.03223010259249852","system_utility":"2256960.7635999564","adt":"1.0399626568521325","shop_utility":"161157.9969575724","uid":"_YlC9_PdzEeyJ463rwa3DNQ","connectivity":"2.0","provided_interface":"1"},"Query Service":{"component_utility":"51154.08927114475","required_interface":"1","request":"56.0","replica":"2.0","failure_name":"None","perf_max":"15.638260292962235","importance":"16.0","reliability":"0.5","criticality":"29.0","sat_point":"0.025129626474919963","system_utility":"2256960.7635999564","adt":"1.3438488200020928","shop_utility":"161157.9969575724","uid":"_YlC97fdzEeyJ463rwa3DNQ","connectivity":"3.0","provided_interface":"2"},"Past Sales Item Filter":{"component_utility":"10034.78742395838","required_interface":"1","request":"64.0","replica":"3.0","failure_name":"None","perf_max":"18.788007171213202","importance":"16.0","reliability":"0.5","criticality":"17.0","sat_point":"0.04282965622198201","system_utility":"2256960.7635999564","adt":"1.1888477181603077","shop_utility":"161157.9969575724","uid":"_YlC99_dzEeyJ463rwa3DNQ","connectivity":"2.0","provided_interface":"1"},"Inventory Service":{"component_utility":"0.0","required_interface":"2","request":"90.0","replica":"3.0","failure_name":"CF3","perf_max":"10.234438874519249","importance":"16.0","reliability":"0.5","criticality":"22.0","sat_point":"0.030309544699775835","system_utility":"2256960.7635999564","adt":"1.0374565589723777","shop_utility":"161157.9969575724","uid":"_YlC94fdzEeyJ463rwa3DNQ","root_issue":"true","connectivity":"3.0","provided_interface":"1"},"Region Item Filter":{"component_utility":"8294.1278757211","required_interface":"1","request":"379.0","replica":"12.0","failure_name":"None","perf_max":"18.545001255145806","importance":"16.0","reliability":"0.5","criticality":"14.0","sat_point":"0.031169668271633928","system_utility":"2256960.7635999564","adt":"1.403268658422189","shop_utility":"161157.9969575724","uid":"_YlC-BvdzEeyJ463rwa3DNQ","connectivity":"2.0","provided_interface":"1"},"Category Item Filter":{"component_utility":"4302.977442339226","required_interface":"1","request":"406.0","replica":"18.0","failure_name":"None","perf_max":"7.311837387771401","importance":"16.0","reliability":"0.5","criticality":"19.0","sat_point":"0.042225913491143234","system_utility":"2256960.7635999564","adt":"1.0619689425785872","shop_utility":"161157.9969575724","uid":"_YlC-F_dzEeyJ463rwa3DNQ","connectivity":"2.0","provided_interface":"1"},"Last Second Sales Item Filter":{"component_utility":"10016.580621455283","required_interface":"1","request":"76.0","replica":"5.0","failure_name":"None","perf_max":"13.387214882587912","importance":"16.0","reliability":"0.5","criticality":"25.0","sat_point":"0.05409054030995984","system_utility":"2256960.7635999564","adt":"1.41912846150458","shop_utility":"161157.9969575724","uid":"_YlC98fdzEeyJ463rwa3DNQ","connectivity":"2.0","provided_interface":"1"},"Future Sales Item Filter":{"component_utility":"4209.447124117768","required_interface":"1","request":"237.0","replica":"14.0","failure_name":"None","perf_max":"7.88766258577082","importance":"16.0","reliability":"0.5","criticality":"17.0","sat_point":"0.055229794880713085","system_utility":"2256960.7635999564","adt":"1.1441322541558454","shop_utility":"161157.9969575724","uid":"_YlC-IvdzEeyJ463rwa3DNQ","connectivity":"2.0","provided_interface":"1"}}}